<?xml version="1.0" encoding="UTF-8"?>
<actions>
        <action>
            <actionName>CUSTOM-skiptests</actionName>
            <displayName>skiptests</displayName>
            <goals>
                <goal>clean</goal>
                <goal>install</goal>
                <goal>-DskipTests=true</goal>
            </goals>
        </action>
        <action>
            <actionName>CUSTOM-mci</actionName>
            <displayName>mci</displayName>
            <goals>
                <goal>clean</goal>
                <goal>install</goal>
            </goals>
        </action>
        <action>
            <actionName>CUSTOM-clean</actionName>
            <displayName>clean</displayName>
            <goals>
                <goal>clean</goal>
            </goals>
        </action>
    </actions>
